helpmeplease/__init__.py
helpmeplease/config.py
helpmeplease/helpme.py
helpmeplease/trackerror.py
helpmeplease-0.1.dist-info/LICENSE
helpmeplease-0.1.dist-info/WHEEL
helpmeplease-0.1.dist-info/METADATA
helpmeplease-0.1.dist-info/RECORD
