Metadata-Version: 2.1
Name: helpmeplease
Version: 0.1
Summary: Ask your friends to debug for you! 
Home-page: https://github.com/Max1993Liu/ask_for_help
License: UNKNOWN
Keywords: Debug Toy Email
Author: Max Liu
Author-email: madmax_liuzhehao@163.com
Requires-Python: >=3
Classifier: License :: OSI Approved :: MIT License
